pydpu/__init__.py
pydpu/__main__.py
pydpu/cli.py
pydpu/dpuredfish/__init__.py
pydpu/dpuredfish/accounts.py
pydpu/dpuredfish/certificates.py
pydpu/dpuredfish/managers.py
pydpu/dpuredfish/systems.py
pydpu/dpuredfish/update.py
pydpu/evpn.py
pydpu/inventory.py
pydpu/ipsec.py
pydpu/proto/__init__.py
pydpu/proto/v1/__init__.py
pydpu/proto/v1/backend_aio_pb2.py
pydpu/proto/v1/backend_aio_pb2_grpc.py
pydpu/proto/v1/backend_iscsi_pb2.py
pydpu/proto/v1/backend_iscsi_pb2_grpc.py
pydpu/proto/v1/backend_malloc_pb2.py
pydpu/proto/v1/backend_malloc_pb2_grpc.py
pydpu/proto/v1/backend_null_pb2.py
pydpu/proto/v1/backend_null_pb2_grpc.py
pydpu/proto/v1/backend_nvme_pb2.py
pydpu/proto/v1/backend_nvme_pb2_grpc.py
pydpu/proto/v1/bgp_pb2.py
pydpu/proto/v1/bgp_pb2_grpc.py
pydpu/proto/v1/cloudrpc_pb2.py
pydpu/proto/v1/cloudrpc_pb2_grpc.py
pydpu/proto/v1/component_pb2.py
pydpu/proto/v1/component_pb2_grpc.py
pydpu/proto/v1/device_pb2.py
pydpu/proto/v1/device_pb2_grpc.py
pydpu/proto/v1/frontend_nvme_pb2.py
pydpu/proto/v1/frontend_nvme_pb2_grpc.py
pydpu/proto/v1/frontend_virtio_blk_pb2.py
pydpu/proto/v1/frontend_virtio_blk_pb2_grpc.py
pydpu/proto/v1/frontend_virtio_fs_pb2.py
pydpu/proto/v1/frontend_virtio_fs_pb2_grpc.py
pydpu/proto/v1/frontend_virtio_scsi_pb2.py
pydpu/proto/v1/frontend_virtio_scsi_pb2_grpc.py
pydpu/proto/v1/interface_pb2.py
pydpu/proto/v1/interface_pb2_grpc.py
pydpu/proto/v1/inventory_pb2.py
pydpu/proto/v1/inventory_pb2_grpc.py
pydpu/proto/v1/ipsec_pb2.py
pydpu/proto/v1/ipsec_pb2_grpc.py
pydpu/proto/v1/k8s_pb2.py
pydpu/proto/v1/k8s_pb2_grpc.py
pydpu/proto/v1/l2_xpu_infra_mgr_pb2.py
pydpu/proto/v1/l2_xpu_infra_mgr_pb2_grpc.py
pydpu/proto/v1/l3_xpu_infra_mgr_pb2.py
pydpu/proto/v1/l3_xpu_infra_mgr_pb2_grpc.py
pydpu/proto/v1/mapping_pb2.py
pydpu/proto/v1/mapping_pb2_grpc.py
pydpu/proto/v1/middleend_encryption_pb2.py
pydpu/proto/v1/middleend_encryption_pb2_grpc.py
pydpu/proto/v1/middleend_qos_volume_pb2.py
pydpu/proto/v1/middleend_qos_volume_pb2_grpc.py
pydpu-0.2.1.dist-info/WHEEL
pydpu-0.2.1.dist-info/LICENSE
pydpu-0.2.1.dist-info/entry_points.txt
pydpu-0.2.1.dist-info/METADATA
pydpu-0.2.1.dist-info/RECORD
