Metadata-Version: 2.1
Name: pydpu
Version: 0.2.1
Summary: Python library and cli to communicate with DPUs and IPUs
License: Apache-2.0
Author: OPI Dev
Author-email: opi-dev@lists.opiproject.org
Requires-Python: >=3.8.1,<4.0
Classifier: License :: OSI Approved :: Apache Software License
Classifier: Programming Language :: Python :: 3
Classifier: Programming Language :: Python :: 3.9
Classifier: Programming Language :: Python :: 3.10
Classifier: Programming Language :: Python :: 3.11
Requires-Dist: Click (>=8.1,<9.0)
Requires-Dist: google (>=3.0.0,<4.0.0)
Requires-Dist: google-api-core (>=2.11.0,<3.0.0)
Requires-Dist: grpcio (>=1.51.1,<2.0.0)
Requires-Dist: redfish (>=3.2.1,<4.0.0)
